MANIFEST.in
setup.py
django_liststyle.egg-info/PKG-INFO
django_liststyle.egg-info/SOURCES.txt
django_liststyle.egg-info/dependency_links.txt
django_liststyle.egg-info/top_level.txt
liststyle/__init__.py
liststyle/admin.py
liststyle/templates/admin/change_list_results.html
liststyle/templates/admin/grappelli_change_list_results.html
liststyle/templatetags/__init__.py
liststyle/templatetags/liststyle_tags.py