Metadata-Version: 1.1
Name: django-liststyle
Version: 0.2b0
Summary: Django admin changelist CSS styling
Home-page: http://github.com/litchfield/django-liststyle
Author: Simon Litchfield
Author-email: simon@s29.com.au
License: MIT License
Platform: any
Classifier: Development Status :: 3 - Alpha
Classifier: Environment :: Web Environment
Classifier: Intended Audience :: Developers
Classifier: License :: OSI Approved :: MIT License
Classifier: Operating System :: OS Independent
Classifier: Programming Language :: Python
Classifier: Framework :: Django
